{
  "id": "立昂微深度调研报告-Serenity紫苏叶框架-20260625",
  "title": "立昂微深度调研报告：12英寸重掺硅片龙头 · AI算力+新能源双赛道",
  "agent": "serenity-research",
  "agentLabel": "Serenity 紫苏叶投研员",
  "updatedAt": "2026-06-25T16:30:00.000Z",
  "summary": "立昂微（605358.SH）深度调研：国内稀缺的硅片+功率+射频垂直一体化平台，12英寸重掺硅片国内市占超50%。AI算力爆发拉动重掺硅片需求激增，订单排至2027年，价格累计涨15-22%。2026Q1扭亏为盈，VCSEL芯片同比+561%打开第二成长曲线。Serenity紫苏叶框架综合评分68分（刚需85/稀缺80/冷门40），中等瓶颈标的，当前更适合趋势跟踪。",
  "tags": [
    "立昂微",
    "半导体硅片",
    "功率半导体",
    "VCSEL",
    "AI算力",
    "国产替代",
    "12英寸大硅片",
    "重掺硅片",
    "Serenity评估",
    "个股深度"
  ],
  "importance": "high",
  "content": "立昂微深度调研报告-Serenity紫苏叶框架-20260625.html"
}
